gempaterkini/__init__.py
gmptrkn-0.0.2.dist-info/LICENSE
gmptrkn-0.0.2.dist-info/METADATA
gmptrkn-0.0.2.dist-info/WHEEL
gmptrkn-0.0.2.dist-info/top_level.txt
gmptrkn-0.0.2.dist-info/RECORD
