Metadata-Version: 2.1
Name: gmptrkn
Version: 0.0.2
Summary: fetch the latest earthquake information from BMKG
Home-page: https://github.com/amelialukis/gmptrkn
Author: Amelia Lukis
Author-email: amelialukis01@gmail.com
License: UNKNOWN
Platform: UNKNOWN
Classifier: Programming Language :: Python :: 3
Classifier: License :: OSI Approved :: GNU Lesser General Public License v3 (LGPLv3)
Classifier: Operating System :: OS Independent
Classifier: Development Status :: 1 - Planning
Requires-Python: >=3.6
License-File: LICENSE
